yaz_templating_plugin/templating.py
yaz_templating_plugin/__init__.py
yaz_templating_plugin/version.py
yaz_templating_plugin-1.0.1.dist-info/WHEEL
yaz_templating_plugin-1.0.1.dist-info/RECORD
yaz_templating_plugin-1.0.1.dist-info/METADATA
yaz_templating_plugin-1.0.1.dist-info/top_level.txt
yaz_templating_plugin-1.0.1.dist-info/DESCRIPTION.rst
yaz_templating_plugin-1.0.1.dist-info/metadata.json
