Metadata-Version: 2.0
Name: yaz-templating-plugin
Version: 1.0.1
Summary: A templating plugin for YAZ
Home-page: https://github.com/yaz/yaz_templating_plugin
Author: Boudewijn Schoon
Author-email: yaz@frayja.com
License: MIT
Platform: UNKNOWN
Classifier: Development Status :: 4 - Beta
Classifier: Environment :: Console
Classifier: License :: OSI Approved :: MIT License
Classifier: Programming Language :: Python :: 3.5
Classifier: Programming Language :: Python :: 3.6
Requires-Dist: yaz
Requires-Dist: jinja2
Requires-Dist: colored
